slck/__init__.py
slck/channel.py
slck/cli.py
slck/message.py
slck/user.py
slck/utils.py
slck_cli-0.3.1.dist-info/entry_points.txt
slck_cli-0.3.1.dist-info/LICENSE
slck_cli-0.3.1.dist-info/WHEEL
slck_cli-0.3.1.dist-info/METADATA
slck_cli-0.3.1.dist-info/RECORD
