Metadata-Version: 2.1
Name: slck-cli
Version: 0.3.1
Summary: Simple cli tool to manage your slack workspace
Home-page: https://github.com/joe-yama/slck-cli
License: MIT
Author: joe-yama
Author-email: s1r0mqme@gmail.com
Requires-Python: >=3.8,<3.10
Classifier: License :: OSI Approved :: MIT License
Classifier: Programming Language :: Python :: 3
Classifier: Programming Language :: Python :: 3.8
Classifier: Programming Language :: Python :: 3.9
Requires-Dist: fire (>=0.4,<0.5)
Requires-Dist: python-dotenv (>=0.19,<0.20)
Requires-Dist: slack-sdk (>=3.0,<4.0)
Project-URL: Repository, https://github.com/joe-yama/slck-cli
